[
  {"id":51,"text":"景行維賢","chars":[{"char":"景","eum":"경","hoon":"볕 경","strokes":12,"radical":"日","origin":"형성","derived":["景色(경색)","風景(풍경)"]},{"char":"行","eum":"행","hoon":"다닐 행","strokes":6,"radical":"行","origin":"상형","derived":["行動(행동)","旅行(여행)"]},{"char":"維","eum":"유","hoon":"벼리 유","strokes":14,"radical":"糸","origin":"형성","derived":["維持(유지)","思維(사유)"]},{"char":"賢","eum":"현","hoon":"어질 현","strokes":15,"radical":"貝","origin":"형성","derived":["賢人(현인)","賢明(현명)"]}],"reading":"경행유현","meaning":"큰 행실은 어진 이를 본받아야 한다","story":"큰 길(景行)처럼 밝은 행실은 어진(賢) 이를 본받는 것입니다.","storyDetail":"《시경》에서 '높은 산을 우러르고 큰 길을 걷는다(高山仰止 景行行止)'에서 유래합니다.","keywords":["시경","현인","본받음"]},
  {"id":52,"text":"克念作聖","chars":[{"char":"克","eum":"극","hoon":"이길 극","strokes":7,"radical":"儿","origin":"형성","derived":["克服(극복)","克己(극기)"]},{"char":"念","eum":"념","hoon":"생각 념","strokes":8,"radical":"心","origin":"형성","derived":["念慮(염려)","記念(기념)"]},{"char":"作","eum":"작","hoon":"지을 작","strokes":7,"radical":"人","origin":"형성","derived":["作品(작품)","製作(제작)"]},{"char":"聖","eum":"성","hoon":"성인 성","strokes":13,"radical":"耳","origin":"형성","derived":["聖人(성인)","神聖(신성)"]}],"reading":"극념작성","meaning":"마음을 이겨내면 성인이 될 수 있다","story":"마음을 이겨(克) 생각(念)을 바르게 하면 성인(聖)이 됩니다(作).","storyDetail":"《서경》의 '마음을 이기면 성인이 되고, 마음에 지면 미치광이가 된다'에서 유래합니다.","keywords":["극기","성인","수양"]},
  {"id":53,"text":"德建名立","chars":[{"char":"德","eum":"덕","hoon":"덕 덕","strokes":15,"radical":"彳","origin":"형성","derived":["道德(도덕)","德行(덕행)"]},{"char":"建","eum":"건","hoon":"세울 건","strokes":9,"radical":"廴","origin":"형성","derived":["建設(건설)","建國(건국)"]},{"char":"名","eum":"명","hoon":"이름 명","strokes":6,"radical":"口","origin":"형성","derived":["名字(명자)","有名(유명)"]},{"char":"立","eum":"립","hoon":"설 립","strokes":5,"radical":"立","origin":"상형","derived":["獨立(독립)","成立(성립)"]}],"reading":"덕건명립","meaning":"덕을 세우면 이름이 선다","story":"덕(德)을 세우면(建) 이름(名)이 저절로 섭니다(立).","storyDetail":"덕행이 먼저이고 명성은 따라오는 것입니다. 입신양명(立身揚名)의 바탕은 덕입니다.","keywords":["덕행","명성","입신"]},
  {"id":54,"text":"形端表正","chars":[{"char":"形","eum":"형","hoon":"모양 형","strokes":7,"radical":"彡","origin":"형성","derived":["形態(형태)","形式(형식)"]},{"char":"端","eum":"단","hoon":"바를 단","strokes":14,"radical":"立","origin":"형성","derived":["端正(단정)","極端(극단)"]},{"char":"表","eum":"표","hoon":"겉 표","strokes":8,"radical":"衣","origin":"형성","derived":["表面(표면)","代表(대표)"]},{"char":"正","eum":"정","hoon":"바를 정","strokes":5,"radical":"止","origin":"형성","derived":["正直(정직)","公正(공정)"]}],"reading":"형단표정","meaning":"모양이 단정하면 겉모습도 바르다","story":"형체(形)가 단정(端)하면 겉모습(表)도 바르게(正) 됩니다.","storyDetail":"내면이 바르면 외면도 바르게 되고, 그림자가 곧은 것은 형체가 곧기 때문입니다.","keywords":["단정","내외","수신"]},
  {"id":55,"text":"空谷傳聲","chars":[{"char":"空","eum":"공","hoon":"빌 공","strokes":8,"radical":"穴","origin":"형성","derived":["空間(공간)","虛空(허공)"]},{"char":"谷","eum":"곡","hoon":"골짜기 곡","strokes":7,"radical":"谷","origin":"상형","derived":["溪谷(계곡)","山谷(산곡)"]},{"char":"傳","eum":"전","hoon":"전할 전","strokes":13,"radical":"人","origin":"형성","derived":["傳達(전달)","傳統(전통)"]},{"char":"聲","eum":"성","hoon":"소리 성","strokes":17,"radical":"耳","origin":"형성","derived":["聲音(성음)","名聲(명성)"]}],"reading":"공곡전성","meaning":"빈 골짜기에 소리가 전해지듯","story":"빈(空) 골짜기(谷)에 소리(聲)가 전해지듯(傳), 덕이 있으면 명성이 저절로 퍼집니다.","storyDetail":"메아리의 비유로, 자기 행실의 결과가 돌아옴을 말합니다. 인과응보의 자연스러운 법칙입니다.","keywords":["메아리","인과","명성"]},
  {"id":56,"text":"虛堂習聽","chars":[{"char":"虛","eum":"허","hoon":"빌 허","strokes":12,"radical":"虍","origin":"형성","derived":["虛空(허공)","虛心(허심)"]},{"char":"堂","eum":"당","hoon":"집 당","strokes":11,"radical":"土","origin":"형성","derived":["堂堂(당당)","食堂(식당)"]},{"char":"習","eum":"습","hoon":"익힐 습","strokes":11,"radical":"羽","origin":"형성","derived":["學習(학습)","練習(연습)"]},{"char":"聽","eum":"청","hoon":"들을 청","strokes":22,"radical":"耳","origin":"형성","derived":["聽取(청취)","傾聽(경청)"]}],"reading":"허당습청","meaning":"빈 집에서 소리가 울리듯","story":"빈(虛) 집(堂)에서 소리가 반복(習)되어 들립니다(聽). 공곡전성과 같은 메아리의 비유입니다.","storyDetail":"빈 방에서 소리가 울리듯, 마음을 비우면 진리가 스며듭니다.","keywords":["허심","경청","수양"]},
  {"id":57,"text":"禍因惡積","chars":[{"char":"禍","eum":"화","hoon":"재앙 화","strokes":14,"radical":"示","origin":"형성","derived":["禍福(화복)","災禍(재화)"]},{"char":"因","eum":"인","hoon":"인할 인","strokes":6,"radical":"囗","origin":"회의","derived":["原因(원인)","因果(인과)"]},{"char":"惡","eum":"악","hoon":"악할 악","strokes":12,"radical":"心","origin":"형성","derived":["善惡(선악)","惡人(악인)"]},{"char":"積","eum":"적","hoon":"쌓을 적","strokes":16,"radical":"禾","origin":"형성","derived":["積極(적극)","蓄積(축적)"]}],"reading":"화인악적","meaning":"재앙은 악이 쌓여서 생긴다","story":"재앙(禍)은 악(惡)이 쌓인(積) 것이 원인(因)입니다.","storyDetail":"《주역》의 '악을 쌓은 집에는 반드시 남는 재앙이 있다(積惡之家 必有餘殃)'에서 유래합니다.","keywords":["인과","주역","재앙"]},
  {"id":58,"text":"福緣善慶","chars":[{"char":"福","eum":"복","hoon":"복 복","strokes":14,"radical":"示","origin":"형성","derived":["幸福(행복)","祝福(축복)"]},{"char":"緣","eum":"연","hoon":"인연 연","strokes":15,"radical":"糸","origin":"형성","derived":["因緣(인연)","緣分(연분)"]},{"char":"善","eum":"선","hoon":"착할 선","strokes":12,"radical":"口","origin":"형성","derived":["善良(선량)","善惡(선악)"]},{"char":"慶","eum":"경","hoon":"경사 경","strokes":15,"radical":"心","origin":"형성","derived":["慶祝(경축)","慶事(경사)"]}],"reading":"복연선경","meaning":"복은 선이 쌓인 경사에서 비롯된다","story":"복(福)은 선(善)한 경사(慶)에 인연(緣)합니다. 앞의 화인악적과 대구를 이룹니다.","storyDetail":"《주역》의 '선을 쌓은 집에는 반드시 남는 경사가 있다(積善之家 必有餘慶)'에서 유래합니다.","keywords":["인과","주역","적선"]},
  {"id":59,"text":"尺璧非寶","chars":[{"char":"尺","eum":"척","hoon":"자 척","strokes":4,"radical":"尸","origin":"상형","derived":["尺度(척도)","尺寸(척촌)"]},{"char":"璧","eum":"벽","hoon":"옥 벽","strokes":18,"radical":"玉","origin":"형성","derived":["完璧(완벽)","白璧(백벽)"]},{"char":"非","eum":"비","hoon":"아닐 비","strokes":8,"radical":"非","origin":"상형","derived":["是非(시비)","非常(비상)"]},{"char":"寶","eum":"보","hoon":"보배 보","strokes":20,"radical":"宀","origin":"형성","derived":["寶物(보물)","國寶(국보)"]}],"reading":"척벽비보","meaning":"한 자 크기의 구슬도 보배가 아니다","story":"한 척(尺)이나 되는 구슬(璧)도 진정한 보배(寶)가 아닙니다(非). 물질보다 시간이 중요하다는 뜻입니다.","storyDetail":"《회남자》에서 '한 자 구슬이 보배가 아니라, 한 치의 시간이 보배(尺璧非寶 寸陰是競)'라 했습니다.","keywords":["시간","가치","회남자"]},
  {"id":60,"text":"寸陰是競","chars":[{"char":"寸","eum":"촌","hoon":"마디 촌","strokes":3,"radical":"寸","origin":"지사","derived":["寸法(촌법)","寸陰(촌음)"]},{"char":"陰","eum":"음","hoon":"그늘 음","strokes":12,"radical":"阜","origin":"형성","derived":["陰陽(음양)","陰影(음영)"]},{"char":"是","eum":"시","hoon":"이 시","strokes":9,"radical":"日","origin":"형성","derived":["是非(시비)","是正(시정)"]},{"char":"競","eum":"경","hoon":"다툴 경","strokes":20,"radical":"立","origin":"형성","derived":["競爭(경쟁)","競走(경주)"]}],"reading":"촌음시경","meaning":"한 치의 시간을 다투어야 한다","story":"한 치(寸)의 시간(陰)이 이것이야말로(是) 다투어야(競) 할 것입니다.","storyDetail":"앞 구절과 이어져 '척벽비보 촌음시경'은 물질보다 시간이 귀하니 아껴 쓰라는 유명한 격언입니다.","keywords":["시간","촌음","격언"]},
  {"id":61,"text":"資父事君","chars":[{"char":"資","eum":"자","hoon":"재물 자","strokes":13,"radical":"貝","origin":"형성","derived":["資本(자본)","投資(투자)"]},{"char":"父","eum":"부","hoon":"아비 부","strokes":4,"radical":"父","origin":"상형","derived":["父母(부모)","父子(부자)"]},{"char":"事","eum":"사","hoon":"일 사","strokes":8,"radical":"亅","origin":"형성","derived":["事件(사건)","事業(사업)"]},{"char":"君","eum":"군","hoon":"임금 군","strokes":7,"radical":"口","origin":"형성","derived":["君主(군주)","君子(군자)"]}],"reading":"자부사군","meaning":"아버지 섬기듯 임금을 섬기고","story":"아버지(父)를 섬기는 것을 바탕(資)으로 임금(君)을 섬깁니다(事).","storyDetail":"효(孝)가 충(忠)의 근본이 된다는 유교적 가르침입니다.","keywords":["충효","부자","군신"]},
  {"id":62,"text":"曰嚴與敬","chars":[{"char":"曰","eum":"왈","hoon":"가로되 왈","strokes":4,"radical":"曰","origin":"상형","derived":["子曰(자왈)"]},{"char":"嚴","eum":"엄","hoon":"엄할 엄","strokes":20,"radical":"口","origin":"형성","derived":["嚴格(엄격)","莊嚴(장엄)"]},{"char":"與","eum":"여","hoon":"줄 여","strokes":14,"radical":"臼","origin":"형성","derived":["參與(참여)","給與(급여)"]},{"char":"敬","eum":"경","hoon":"공경할 경","strokes":13,"radical":"攵","origin":"형성","derived":["尊敬(존경)","敬語(경어)"]}],"reading":"왈엄여경","meaning":"엄숙함과 공경함이라 하였다","story":"부모와 임금을 섬기는 태도는 엄숙함(嚴)과 공경함(敬)이라 하였습니다(曰).","storyDetail":"《효경》에서 효와 충의 근본 태도를 엄경(嚴敬)으로 요약합니다.","keywords":["엄경","효경","태도"]},
  {"id":63,"text":"孝當竭力","chars":[{"char":"孝","eum":"효","hoon":"효도 효","strokes":7,"radical":"子","origin":"회의","derived":["孝道(효도)","孝子(효자)"]},{"char":"當","eum":"당","hoon":"마땅 당","strokes":13,"radical":"田","origin":"형성","derived":["當然(당연)","正當(정당)"]},{"char":"竭","eum":"갈","hoon":"다할 갈","strokes":14,"radical":"立","origin":"형성","derived":["竭力(갈력)","枯竭(고갈)"]},{"char":"力","eum":"력","hoon":"힘 력","strokes":2,"radical":"力","origin":"상형","derived":["努力(노력)","能力(능력)"]}],"reading":"효당갈력","meaning":"효도에는 마땅히 힘을 다해야 한다","story":"효도(孝)에는 마땅히(當) 힘(力)을 다해야(竭) 합니다.","storyDetail":"부모를 섬기는 데 힘을 다하는 것이 효의 실천입니다.","keywords":["효도","실천","진력"]},
  {"id":64,"text":"忠則盡命","chars":[{"char":"忠","eum":"충","hoon":"충성 충","strokes":8,"radical":"心","origin":"형성","derived":["忠誠(충성)","忠臣(충신)"]},{"char":"則","eum":"즉","hoon":"곧 즉","strokes":9,"radical":"刀","origin":"형성","derived":["法則(법칙)","規則(규칙)"]},{"char":"盡","eum":"진","hoon":"다할 진","strokes":14,"radical":"皿","origin":"형성","derived":["盡力(진력)","盡忠(진충)"]},{"char":"命","eum":"명","hoon":"목숨 명","strokes":8,"radical":"口","origin":"형성","derived":["生命(생명)","運命(운명)"]}],"reading":"충즉진명","meaning":"충성에는 곧 목숨을 다해야 한다","story":"충성(忠)에는 곧(則) 목숨(命)을 다해야(盡) 합니다.","storyDetail":"효당갈력과 대구를 이루며, 충신의 도리를 강조합니다.","keywords":["충성","진명","충신"]},
  {"id":65,"text":"臨深履薄","chars":[{"char":"臨","eum":"림","hoon":"임할 림","strokes":17,"radical":"臣","origin":"형성","derived":["臨時(임시)","臨終(임종)"]},{"char":"深","eum":"심","hoon":"깊을 심","strokes":11,"radical":"水","origin":"형성","derived":["深海(심해)","深刻(심각)"]},{"char":"履","eum":"리","hoon":"밟을 리","strokes":15,"radical":"尸","origin":"형성","derived":["履行(이행)","履歷(이력)"]},{"char":"薄","eum":"박","hoon":"얇을 박","strokes":16,"radical":"艸","origin":"형성","derived":["薄弱(박약)","輕薄(경박)"]}],"reading":"림심리박","meaning":"깊은 못에 임하듯 얇은 얼음을 밟듯","story":"깊은(深) 못에 임하듯(臨), 얇은(薄) 얼음을 밟듯(履) 조심해야 합니다.","storyDetail":"《시경》의 '전전긍긍 여림심연 여리박빙'에서 유래한 표현으로, 늘 삼가는 태도를 가르칩니다.","keywords":["삼가","시경","조심"]},
  {"id":66,"text":"夙興溫凊","chars":[{"char":"夙","eum":"숙","hoon":"일찍 숙","strokes":6,"radical":"大","origin":"형성","derived":["夙夜(숙야)","夙願(숙원)"]},{"char":"興","eum":"흥","hoon":"일어날 흥","strokes":16,"radical":"臼","origin":"형성","derived":["興起(흥기)","復興(부흥)"]},{"char":"溫","eum":"온","hoon":"따뜻할 온","strokes":13,"radical":"水","origin":"형성","derived":["溫度(온도)","溫和(온화)"]},{"char":"凊","eum":"청","hoon":"서늘할 청","strokes":10,"radical":"冫","origin":"형성","derived":["凊涼(청량)"]}],"reading":"숙흥온청","meaning":"일찍 일어나 부모의 잠자리를 살피고","story":"일찍(夙) 일어나(興) 겨울에는 따뜻하게(溫), 여름에는 서늘하게(凊) 부모의 잠자리를 돌봅니다.","storyDetail":"동온하청(冬溫夏凊)은 부모에 대한 효도의 구체적 실천 방법입니다.","keywords":["효도","온청","실천"]},
  {"id":67,"text":"似蘭斯馨","chars":[{"char":"似","eum":"사","hoon":"닮을 사","strokes":7,"radical":"人","origin":"형성","derived":["類似(유사)","相似(상사)"]},{"char":"蘭","eum":"란","hoon":"난초 란","strokes":20,"radical":"艸","origin":"형성","derived":["蘭花(난화)","芝蘭(지란)"]},{"char":"斯","eum":"사","hoon":"이 사","strokes":12,"radical":"斤","origin":"형성","derived":["如斯(여사)"]},{"char":"馨","eum":"형","hoon":"향기 형","strokes":20,"radical":"香","origin":"형성","derived":["馨香(형향)"]}],"reading":"사란사형","meaning":"난초처럼 향기가 나느니","story":"난초(蘭)처럼(似) 그 향기(馨)가 은은하게 퍼집니다. 군자의 덕행을 꽃에 비유합니다.","storyDetail":"공자는 '지란지실(芝蘭之室)에 들어가면 향기를 모른다'며 좋은 환경의 중요성을 말했습니다.","keywords":["난초","군자","향기"]},
  {"id":68,"text":"如松之盛","chars":[{"char":"如","eum":"여","hoon":"같을 여","strokes":6,"radical":"女","origin":"형성","derived":["如意(여의)","如何(여하)"]},{"char":"松","eum":"송","hoon":"소나무 송","strokes":8,"radical":"木","origin":"형성","derived":["松柏(송백)","靑松(청송)"]},{"char":"之","eum":"지","hoon":"갈 지","strokes":4,"radical":"丶","origin":"지사","derived":["之前(지전)"]},{"char":"盛","eum":"성","hoon":"성할 성","strokes":12,"radical":"皿","origin":"형성","derived":["盛大(성대)","繁盛(번성)"]}],"reading":"여송지성","meaning":"소나무처럼 무성하니","story":"소나무(松)처럼(如) 무성(盛)합니다. 사시사철 푸른 소나무는 군자의 절개를 상징합니다.","storyDetail":"소나무와 잣나무(松柏)는 추위에도 푸른 절개의 상징으로, 군자의 변치 않는 덕을 비유합니다.","keywords":["소나무","절개","군자"]},
  {"id":69,"text":"川流不息","chars":[{"char":"川","eum":"천","hoon":"내 천","strokes":3,"radical":"川","origin":"상형","derived":["山川(산천)","河川(하천)"]},{"char":"流","eum":"류","hoon":"흐를 류","strokes":10,"radical":"水","origin":"형성","derived":["流水(유수)","潮流(조류)"]},{"char":"不","eum":"불","hoon":"아닐 불","strokes":4,"radical":"一","origin":"상형","derived":["不可(불가)","不足(부족)"]},{"char":"息","eum":"식","hoon":"쉴 식","strokes":10,"radical":"心","origin":"형성","derived":["休息(휴식)","利息(이식)"]}],"reading":"천류불식","meaning":"강물이 흐르듯 쉬지 않으니","story":"강물(川)이 흘러(流) 쉬지(息) 않는(不) 것처럼, 군자의 수양도 끊임없이 이어져야 합니다.","storyDetail":"공자의 '물이여! 물이여!(逝者如斯夫 不舍晝夜)'라는 탄식과 통합니다.","keywords":["수양","끊임없음","공자"]},
  {"id":70,"text":"淵澄取映","chars":[{"char":"淵","eum":"연","hoon":"못 연","strokes":12,"radical":"水","origin":"형성","derived":["深淵(심연)","淵源(연원)"]},{"char":"澄","eum":"징","hoon":"맑을 징","strokes":15,"radical":"水","origin":"형성","derived":["澄淸(징청)"]},{"char":"取","eum":"취","hoon":"취할 취","strokes":8,"radical":"又","origin":"형성","derived":["取得(취득)","選取(선취)"]},{"char":"映","eum":"영","hoon":"비칠 영","strokes":9,"radical":"日","origin":"형성","derived":["反映(반영)","映像(영상)"]}],"reading":"연징취영","meaning":"맑은 못에 그림자가 비치듯","story":"못(淵)이 맑으면(澄) 그림자(映)를 비추듯(取), 마음이 맑으면 만물이 비칩니다.","storyDetail":"군자의 마음은 맑은 못과 같아서 만물의 진상이 저절로 비친다는 비유입니다.","keywords":["마음","맑음","비침"]},
  {"id":71,"text":"容止若思","chars":[{"char":"容","eum":"용","hoon":"얼굴 용","strokes":10,"radical":"宀","origin":"형성","derived":["容貌(용모)","包容(포용)"]},{"char":"止","eum":"지","hoon":"그칠 지","strokes":4,"radical":"止","origin":"상형","derived":["停止(정지)","禁止(금지)"]},{"char":"若","eum":"약","hoon":"같을 약","strokes":8,"radical":"艸","origin":"형성","derived":["若干(약간)","若者(약자)"]},{"char":"思","eum":"사","hoon":"생각 사","strokes":9,"radical":"心","origin":"형성","derived":["思想(사상)","思考(사고)"]}],"reading":"용지약사","meaning":"용모와 거동은 생각하는 듯이","story":"용모(容)와 거동(止)은 생각하는(思) 듯(若) 차분해야 합니다.","storyDetail":"《예기》에서 군자의 구용(九容) 중 하나로, 외모의 단정함을 강조합니다.","keywords":["구용","예기","단정"]},
  {"id":72,"text":"言辭安定","chars":[{"char":"言","eum":"언","hoon":"말씀 언","strokes":7,"radical":"言","origin":"상형","derived":["言語(언어)","發言(발언)"]},{"char":"辭","eum":"사","hoon":"말씀 사","strokes":19,"radical":"辛","origin":"형성","derived":["辭典(사전)","辭退(사퇴)"]},{"char":"安","eum":"안","hoon":"편안 안","strokes":6,"radical":"宀","origin":"회의","derived":["安全(안전)","安定(안정)"]},{"char":"定","eum":"정","hoon":"정할 정","strokes":8,"radical":"宀","origin":"형성","derived":["決定(결정)","安定(안정)"]}],"reading":"언사안정","meaning":"말은 안정되어야 한다","story":"말(言辭)은 편안하고(安) 안정되게(定) 해야 합니다. 군자의 언행에 대한 가르침입니다.","storyDetail":"말을 함부로 하지 않고 신중하게 하는 것이 군자의 기본 덕목입니다.","keywords":["언행","신중","군자"]},
  {"id":73,"text":"篤初誠美","chars":[{"char":"篤","eum":"독","hoon":"도타울 독","strokes":16,"radical":"竹","origin":"형성","derived":["篤實(독실)","篤志(독지)"]},{"char":"初","eum":"초","hoon":"처음 초","strokes":7,"radical":"刀","origin":"형성","derived":["最初(최초)","初心(초심)"]},{"char":"誠","eum":"성","hoon":"정성 성","strokes":14,"radical":"言","origin":"형성","derived":["誠實(성실)","至誠(지성)"]},{"char":"美","eum":"미","hoon":"아름다울 미","strokes":9,"radical":"羊","origin":"형성","derived":["美麗(미려)","美德(미덕)"]}],"reading":"독초성미","meaning":"처음을 도탑게 하면 참으로 아름답고","story":"처음(初)을 도탑게(篤) 하면 참으로(誠) 아름답습니다(美). 시작을 잘하라는 가르침입니다.","storyDetail":"모든 일의 성패는 처음 마음가짐에 달려 있으므로 초심을 잃지 말라는 뜻입니다.","keywords":["초심","시작","정성"]},
  {"id":74,"text":"慎終宜令","chars":[{"char":"慎","eum":"신","hoon":"삼갈 신","strokes":13,"radical":"心","origin":"형성","derived":["愼重(신중)","謹慎(근신)"]},{"char":"終","eum":"종","hoon":"마칠 종","strokes":11,"radical":"糸","origin":"형성","derived":["終了(종료)","最終(최종)"]},{"char":"宜","eum":"의","hoon":"마땅 의","strokes":8,"radical":"宀","origin":"형성","derived":["適宜(적의)","便宜(편의)"]},{"char":"令","eum":"령","hoon":"하여금 령","strokes":5,"radical":"人","origin":"형성","derived":["命令(명령)","法令(법령)"]}],"reading":"신종의령","meaning":"끝을 삼가면 마땅히 아름답다","story":"끝(終)을 삼가면(慎) 마땅히(宜) 훌륭합니다(令). 유종의 미를 거두라는 뜻입니다.","storyDetail":"독초성미와 대구로, 시작과 끝을 모두 잘해야 한다는 가르침입니다. 신종여시(愼終如始).","keywords":["유종","마무리","삼가"]},
  {"id":75,"text":"榮業所基","chars":[{"char":"榮","eum":"영","hoon":"영화 영","strokes":14,"radical":"木","origin":"형성","derived":["榮光(영광)","繁榮(번영)"]},{"char":"業","eum":"업","hoon":"업 업","strokes":13,"radical":"木","origin":"형성","derived":["事業(사업)","職業(직업)"]},{"char":"所","eum":"소","hoon":"바 소","strokes":8,"radical":"戶","origin":"형성","derived":["場所(장소)","所有(소유)"]},{"char":"基","eum":"기","hoon":"터 기","strokes":11,"radical":"土","origin":"형성","derived":["基礎(기초)","基本(기본)"]}],"reading":"영업소기","meaning":"영화로운 업적의 바탕이 되니","story":"영화로운(榮) 업적(業)의 바탕(基)이 되는 바(所)입니다.","storyDetail":"덕행과 학문이 영화로운 사업의 기초가 된다는 뜻입니다.","keywords":["영화","기초","업적"]},
  {"id":76,"text":"籍甚無竟","chars":[{"char":"籍","eum":"적","hoon":"문서 적","strokes":20,"radical":"竹","origin":"형성","derived":["書籍(서적)","戶籍(호적)"]},{"char":"甚","eum":"심","hoon":"심할 심","strokes":9,"radical":"甘","origin":"형성","derived":["甚至(심지)","過甚(과심)"]},{"char":"無","eum":"무","hoon":"없을 무","strokes":12,"radical":"火","origin":"형성","derived":["無限(무한)","無事(무사)"]},{"char":"竟","eum":"경","hoon":"다할 경","strokes":11,"radical":"立","origin":"형성","derived":["究竟(구경)","畢竟(필경)"]}],"reading":"적심무경","meaning":"명성이 심히 끝이 없다","story":"명성(籍)이 심히(甚) 끝(竟)이 없습니다(無). 덕업의 영향이 무한히 이어진다는 뜻입니다.","storyDetail":"영업소기와 이어져, 덕에 기초한 업적은 그 명성이 끝없이 전해진다는 것을 말합니다.","keywords":["명성","무한","덕업"]},
  {"id":77,"text":"學優登仕","chars":[{"char":"學","eum":"학","hoon":"배울 학","strokes":16,"radical":"子","origin":"형성","derived":["學問(학문)","學校(학교)"]},{"char":"優","eum":"우","hoon":"넉넉할 우","strokes":17,"radical":"人","origin":"형성","derived":["優秀(우수)","優待(우대)"]},{"char":"登","eum":"등","hoon":"오를 등","strokes":12,"radical":"癶","origin":"형성","derived":["登山(등산)","登錄(등록)"]},{"char":"仕","eum":"사","hoon":"섬길 사","strokes":5,"radical":"人","origin":"형성","derived":["仕官(사관)","出仕(출사)"]}],"reading":"학우등사","meaning":"학문이 넉넉하면 벼슬에 오르고","story":"학문(學)이 넉넉하면(優) 벼슬(仕)에 오릅니다(登).","storyDetail":"《논어》의 '학이우즉사(學而優則仕)'에서 유래합니다. 배움의 목적이 사회 봉사임을 말합니다.","keywords":["논어","출사","배움"]},
  {"id":78,"text":"攝職從政","chars":[{"char":"攝","eum":"섭","hoon":"잡을 섭","strokes":21,"radical":"手","origin":"형성","derived":["攝政(섭정)","攝取(섭취)"]},{"char":"職","eum":"직","hoon":"직분 직","strokes":18,"radical":"耳","origin":"형성","derived":["職業(직업)","職務(직무)"]},{"char":"從","eum":"종","hoon":"쫓을 종","strokes":11,"radical":"彳","origin":"형성","derived":["從事(종사)","服從(복종)"]},{"char":"政","eum":"정","hoon":"정사 정","strokes":9,"radical":"攵","origin":"형성","derived":["政治(정치)","政策(정책)"]}],"reading":"섭직종정","meaning":"직분을 맡아 정사에 종사하니","story":"직분(職)을 맡아(攝) 정사(政)에 종사(從)합니다.","storyDetail":"학우등사와 이어져, 학문을 갈고닦아 관직에 나아가 정치에 참여하는 과정을 말합니다.","keywords":["관직","정치","봉사"]},
  {"id":79,"text":"存以甘棠","chars":[{"char":"存","eum":"존","hoon":"있을 존","strokes":6,"radical":"子","origin":"형성","derived":["存在(존재)","保存(보존)"]},{"char":"以","eum":"이","hoon":"써 이","strokes":5,"radical":"人","origin":"형성","derived":["以上(이상)","以後(이후)"]},{"char":"甘","eum":"감","hoon":"달 감","strokes":5,"radical":"甘","origin":"상형","derived":["甘味(감미)","甘草(감초)"]},{"char":"棠","eum":"당","hoon":"아가위 당","strokes":12,"radical":"木","origin":"형성","derived":["甘棠(감당)","海棠(해당)"]}],"reading":"존이감당","meaning":"감당나무를 보존하듯","story":"감당(甘棠)나무를 보존(存)하듯, 선정을 베푼 관리의 유산을 지킵니다.","storyDetail":"소공(召公)이 감당나무 아래에서 선정을 베풀어, 백성이 그 나무를 소중히 보존한 고사입니다.","keywords":["소공","선정","감당"]},
  {"id":80,"text":"去而益詠","chars":[{"char":"去","eum":"거","hoon":"갈 거","strokes":5,"radical":"厶","origin":"형성","derived":["去來(거래)","過去(과거)"]},{"char":"而","eum":"이","hoon":"말이을 이","strokes":6,"radical":"而","origin":"상형","derived":["而且(이차)"]},{"char":"益","eum":"익","hoon":"더할 익","strokes":10,"radical":"皿","origin":"형성","derived":["利益(이익)","有益(유익)"]},{"char":"詠","eum":"영","hoon":"읊을 영","strokes":12,"radical":"言","origin":"형성","derived":["詠歌(영가)","詠嘆(영탄)"]}],"reading":"거이익영","meaning":"떠난 뒤에 더욱 노래하였다","story":"소공이 떠난(去) 뒤에(而) 백성들이 더욱(益) 그 덕을 노래(詠)했습니다.","storyDetail":"존이감당과 이어져, 어진 관리가 떠난 뒤에도 그 덕을 칭송하는 아름다운 전통을 말합니다.","keywords":["칭송","유산","덕치"]},
  {"id":81,"text":"樂殊貴賤","chars":[{"char":"樂","eum":"악","hoon":"풍류 악","strokes":15,"radical":"木","origin":"형성","derived":["音樂(음악)","樂器(악기)"]},{"char":"殊","eum":"수","hoon":"다를 수","strokes":10,"radical":"歹","origin":"형성","derived":["特殊(특수)","殊勝(수승)"]},{"char":"貴","eum":"귀","hoon":"귀할 귀","strokes":12,"radical":"貝","origin":"형성","derived":["貴族(귀족)","尊貴(존귀)"]},{"char":"賤","eum":"천","hoon":"천할 천","strokes":15,"radical":"貝","origin":"형성","derived":["卑賤(비천)","貴賤(귀천)"]}],"reading":"악수귀천","meaning":"음악은 귀하고 천한 이에 따라 다르고","story":"음악(樂)은 귀한(貴) 이와 천한(賤) 이에 따라 다릅니다(殊).","storyDetail":"예악(禮樂) 제도에서 신분에 따라 음악이 달랐음을 말합니다.","keywords":["예악","귀천","신분"]},
  {"id":82,"text":"禮別尊卑","chars":[{"char":"禮","eum":"례","hoon":"예도 례","strokes":18,"radical":"示","origin":"형성","derived":["禮儀(예의)","禮節(예절)"]},{"char":"別","eum":"별","hoon":"나눌 별","strokes":7,"radical":"刀","origin":"형성","derived":["區別(구별)","特別(특별)"]},{"char":"尊","eum":"존","hoon":"높을 존","strokes":12,"radical":"寸","origin":"형성","derived":["尊敬(존경)","尊嚴(존엄)"]},{"char":"卑","eum":"비","hoon":"낮을 비","strokes":8,"radical":"十","origin":"형성","derived":["卑下(비하)","卑賤(비천)"]}],"reading":"례별존비","meaning":"예절은 높고 낮은 이를 구별한다","story":"예(禮)는 높은(尊) 이와 낮은(卑) 이를 구별(別)합니다.","storyDetail":"악수귀천과 대구로, 예와 악이 사회 질서의 근간임을 말합니다.","keywords":["예절","존비","질서"]},
  {"id":83,"text":"上和下睦","chars":[{"char":"上","eum":"상","hoon":"위 상","strokes":3,"radical":"一","origin":"지사","derived":["上下(상하)","以上(이상)"]},{"char":"和","eum":"화","hoon":"화할 화","strokes":8,"radical":"口","origin":"형성","derived":["和平(화평)","調和(조화)"]},{"char":"下","eum":"하","hoon":"아래 하","strokes":3,"radical":"一","origin":"지사","derived":["上下(상하)","以下(이하)"]},{"char":"睦","eum":"목","hoon":"화목할 목","strokes":13,"radical":"目","origin":"형성","derived":["和睦(화목)","親睦(친목)"]}],"reading":"상화하목","meaning":"윗사람은 화목하고 아랫사람은 친목하니","story":"윗사람(上)은 화목하고(和), 아랫사람(下)은 친목(睦)합니다.","storyDetail":"위아래가 서로 화합하여 가정과 사회의 질서가 유지됩니다.","keywords":["화목","상하","질서"]},
  {"id":84,"text":"夫唱婦隨","chars":[{"char":"夫","eum":"부","hoon":"지아비 부","strokes":4,"radical":"大","origin":"상형","derived":["夫人(부인)","丈夫(장부)"]},{"char":"唱","eum":"창","hoon":"부를 창","strokes":11,"radical":"口","origin":"형성","derived":["唱歌(창가)","合唱(합창)"]},{"char":"婦","eum":"부","hoon":"며느리 부","strokes":11,"radical":"女","origin":"형성","derived":["婦人(부인)","夫婦(부부)"]},{"char":"隨","eum":"수","hoon":"따를 수","strokes":16,"radical":"阜","origin":"형성","derived":["隨行(수행)","追隨(추수)"]}],"reading":"부창부수","meaning":"남편이 부르면 아내가 따르니","story":"남편(夫)이 부르면(唱) 아내(婦)가 따릅니다(隨). 부부간의 화합을 말합니다.","storyDetail":"부부가 서로 존중하며 조화롭게 살아가는 것이 가정 질서의 근본입니다.","keywords":["부부","화합","가정"]},
  {"id":85,"text":"外受傅訓","chars":[{"char":"外","eum":"외","hoon":"바깥 외","strokes":5,"radical":"夕","origin":"형성","derived":["外部(외부)","海外(해외)"]},{"char":"受","eum":"수","hoon":"받을 수","strokes":8,"radical":"又","origin":"형성","derived":["受業(수업)","受容(수용)"]},{"char":"傅","eum":"부","hoon":"스승 부","strokes":12,"radical":"人","origin":"형성","derived":["師傅(사부)","太傅(태부)"]},{"char":"訓","eum":"훈","hoon":"가르칠 훈","strokes":10,"radical":"言","origin":"형성","derived":["訓練(훈련)","教訓(교훈)"]}],"reading":"외수부훈","meaning":"밖에서는 스승의 가르침을 받고","story":"밖(外)에서는 스승(傅)의 가르침(訓)을 받습니다(受).","storyDetail":"집 밖에서는 스승의 교훈을 따르고, 집 안에서는 어머니의 가르침을 따르라는 뜻입니다.","keywords":["스승","교훈","배움"]},
  {"id":86,"text":"入奉母儀","chars":[{"char":"入","eum":"입","hoon":"들 입","strokes":2,"radical":"入","origin":"상형","derived":["入學(입학)","收入(수입)"]},{"char":"奉","eum":"봉","hoon":"받들 봉","strokes":8,"radical":"大","origin":"형성","derived":["奉仕(봉사)","奉行(봉행)"]},{"char":"母","eum":"모","hoon":"어미 모","strokes":5,"radical":"毋","origin":"상형","derived":["母親(모친)","父母(부모)"]},{"char":"儀","eum":"의","hoon":"거동 의","strokes":15,"radical":"人","origin":"형성","derived":["禮儀(예의)","儀式(의식)"]}],"reading":"입봉모의","meaning":"안에서는 어머니의 가르침을 받든다","story":"안(入)에서는 어머니(母)의 법도(儀)를 받듭니다(奉).","storyDetail":"외수부훈과 대구로, 안팎에서의 교육을 균형 있게 받아야 함을 말합니다.","keywords":["어머니","법도","가정교육"]},
  {"id":87,"text":"諸姑伯叔","chars":[{"char":"諸","eum":"제","hoon":"모든 제","strokes":16,"radical":"言","origin":"형성","derived":["諸般(제반)","諸侯(제후)"]},{"char":"姑","eum":"고","hoon":"시어미 고","strokes":8,"radical":"女","origin":"형성","derived":["姑母(고모)","翁姑(옹고)"]},{"char":"伯","eum":"백","hoon":"맏 백","strokes":7,"radical":"人","origin":"형성","derived":["伯父(백부)","伯仲(백중)"]},{"char":"叔","eum":"숙","hoon":"아재비 숙","strokes":8,"radical":"又","origin":"형성","derived":["叔父(숙부)","叔母(숙모)"]}],"reading":"제고백숙","meaning":"고모와 백부 숙부에게는","story":"여러(諸) 고모(姑)와 백부(伯), 숙부(叔) 등 친척 어른을 말합니다.","storyDetail":"집안의 친척 어른들에게도 예를 갖추어야 한다는 가르침입니다.","keywords":["친척","가족","윤리"]},
  {"id":88,"text":"猶子比兒","chars":[{"char":"猶","eum":"유","hoon":"오히려 유","strokes":13,"radical":"犬","origin":"형성","derived":["猶豫(유예)","猶如(유여)"]},{"char":"子","eum":"자","hoon":"아들 자","strokes":3,"radical":"子","origin":"상형","derived":["子女(자녀)","子孫(자손)"]},{"char":"比","eum":"비","hoon":"견줄 비","strokes":4,"radical":"比","origin":"회의","derived":["比較(비교)","比率(비율)"]},{"char":"兒","eum":"아","hoon":"아이 아","strokes":8,"radical":"儿","origin":"상형","derived":["兒童(아동)","幼兒(유아)"]}],"reading":"유자비아","meaning":"자기 자식처럼 여겨야 한다","story":"조카를 자기 아들(子)처럼(猶) 자기 아이(兒)에 견줍니다(比).","storyDetail":"제고백숙과 이어져, 친척의 자녀도 자기 자식처럼 아끼라는 가르침입니다.","keywords":["조카","가족애","친척"]},
  {"id":89,"text":"孔懷兄弟","chars":[{"char":"孔","eum":"공","hoon":"구멍 공","strokes":4,"radical":"子","origin":"형성","derived":["孔子(공자)","孔雀(공작)"]},{"char":"懷","eum":"회","hoon":"품을 회","strokes":19,"radical":"心","origin":"형성","derived":["懷抱(회포)","懷念(회념)"]},{"char":"兄","eum":"형","hoon":"형 형","strokes":5,"radical":"儿","origin":"회의","derived":["兄弟(형제)","父兄(부형)"]},{"char":"弟","eum":"제","hoon":"아우 제","strokes":7,"radical":"弓","origin":"형성","derived":["兄弟(형제)","弟子(제자)"]}],"reading":"공회형제","meaning":"형제간에 매우 그리워하며","story":"형제(兄弟)간에 매우(孔) 그리워합니다(懷). 형제간의 깊은 우애를 말합니다.","storyDetail":"《시경》에서 '형제를 매우 그리워한다(兄弟孔懷)'에서 나온 표현입니다.","keywords":["형제","우애","시경"]},
  {"id":90,"text":"同氣連枝","chars":[{"char":"同","eum":"동","hoon":"한가지 동","strokes":6,"radical":"口","origin":"형성","derived":["同一(동일)","共同(공동)"]},{"char":"氣","eum":"기","hoon":"기운 기","strokes":10,"radical":"气","origin":"형성","derived":["氣運(기운)","元氣(원기)"]},{"char":"連","eum":"련","hoon":"이을 련","strokes":10,"radical":"辵","origin":"형성","derived":["連結(연결)","連續(연속)"]},{"char":"枝","eum":"지","hoon":"가지 지","strokes":8,"radical":"木","origin":"형성","derived":["枝葉(지엽)","樹枝(수지)"]}],"reading":"동기연지","meaning":"같은 기운의 이어진 가지와 같다","story":"같은(同) 기운(氣)의 이어진(連) 가지(枝)처럼, 형제는 한 뿌리에서 나온 것입니다.","storyDetail":"형제를 나무의 가지에 비유하여, 근본이 같으므로 서로 아끼라는 뜻입니다.","keywords":["형제","동기","가족"]},
  {"id":91,"text":"交友投分","chars":[{"char":"交","eum":"교","hoon":"사귈 교","strokes":6,"radical":"亠","origin":"상형","derived":["交流(교류)","交際(교제)"]},{"char":"友","eum":"우","hoon":"벗 우","strokes":4,"radical":"又","origin":"회의","derived":["友情(우정)","朋友(붕우)"]},{"char":"投","eum":"투","hoon":"던질 투","strokes":7,"radical":"手","origin":"형성","derived":["投資(투자)","投票(투표)"]},{"char":"分","eum":"분","hoon":"나눌 분","strokes":4,"radical":"刀","origin":"형성","derived":["分類(분류)","分配(분배)"]}],"reading":"교우투분","meaning":"벗을 사귀되 분수에 맞게 하고","story":"벗(友)을 사귀되(交) 분수(分)에 맞게 투합(投)해야 합니다.","storyDetail":"친구 관계에서도 분수와 의리를 지켜야 한다는 가르침입니다.","keywords":["우정","분수","의리"]},
  {"id":92,"text":"切磨箴規","chars":[{"char":"切","eum":"절","hoon":"끊을 절","strokes":4,"radical":"刀","origin":"형성","derived":["切實(절실)","親切(친절)"]},{"char":"磨","eum":"마","hoon":"갈 마","strokes":16,"radical":"石","origin":"형성","derived":["硏磨(연마)","磨滅(마멸)"]},{"char":"箴","eum":"잠","hoon":"경계할 잠","strokes":15,"radical":"竹","origin":"형성","derived":["箴言(잠언)","箴規(잠규)"]},{"char":"規","eum":"규","hoon":"법 규","strokes":11,"radical":"見","origin":"형성","derived":["規則(규칙)","規範(규범)"]}],"reading":"절마잠규","meaning":"서로 갈고 닦으며 충고하고 바로잡는다","story":"서로 끊고(切) 갈며(磨), 경계하고(箴) 바로잡습니다(規). 벗 사이의 도리입니다.","storyDetail":"절차탁마(切磋琢磨)에서 유래하며, 진정한 친구란 서로 발전하도록 돕는 관계입니다.","keywords":["절차탁마","충고","교우"]},
  {"id":93,"text":"仁慈隱惻","chars":[{"char":"仁","eum":"인","hoon":"어질 인","strokes":4,"radical":"人","origin":"형성","derived":["仁慈(인자)","仁德(인덕)"]},{"char":"慈","eum":"자","hoon":"사랑 자","strokes":13,"radical":"心","origin":"형성","derived":["慈悲(자비)","慈愛(자애)"]},{"char":"隱","eum":"은","hoon":"숨을 은","strokes":17,"radical":"阜","origin":"형성","derived":["隱居(은거)","隱忍(은인)"]},{"char":"惻","eum":"측","hoon":"슬퍼할 측","strokes":11,"radical":"心","origin":"형성","derived":["惻隱(측은)","惻愴(측창)"]}],"reading":"인자은측","meaning":"어질고 자비로우며 측은히 여기고","story":"어질고(仁) 자비로우며(慈), 남의 고통을 숨기듯(隱) 슬퍼합니다(惻).","storyDetail":"맹자의 사단(四端) 중 측은지심(惻隱之心)은 인(仁)의 시작입니다.","keywords":["인자","측은","사단"]},
  {"id":94,"text":"造次弗離","chars":[{"char":"造","eum":"조","hoon":"지을 조","strokes":10,"radical":"辵","origin":"형성","derived":["創造(창조)","造成(조성)"]},{"char":"次","eum":"차","hoon":"버금 차","strokes":6,"radical":"欠","origin":"형성","derived":["次第(차제)","順次(순차)"]},{"char":"弗","eum":"불","hoon":"아닐 불","strokes":5,"radical":"弓","origin":"형성","derived":["弗堪(불감)"]},{"char":"離","eum":"리","hoon":"떠날 리","strokes":19,"radical":"隹","origin":"형성","derived":["離別(이별)","離散(이산)"]}],"reading":"조차불리","meaning":"급한 때에도 떠나지 않는다","story":"급박한(造次) 때에도 인자함을 떠나지(離) 않습니다(弗).","storyDetail":"《논어》에서 '군자는 밥 먹는 사이에도 인을 떠나지 않는다(造次必於是)'에서 유래합니다.","keywords":["논어","인","수양"]},
  {"id":95,"text":"節義廉退","chars":[{"char":"節","eum":"절","hoon":"마디 절","strokes":13,"radical":"竹","origin":"형성","derived":["節義(절의)","節約(절약)"]},{"char":"義","eum":"의","hoon":"옳을 의","strokes":13,"radical":"羊","origin":"형성","derived":["正義(정의)","義理(의리)"]},{"char":"廉","eum":"렴","hoon":"청렴 렴","strokes":13,"radical":"广","origin":"형성","derived":["廉潔(염결)","廉恥(염치)"]},{"char":"退","eum":"퇴","hoon":"물러갈 퇴","strokes":9,"radical":"辵","origin":"형성","derived":["退職(퇴직)","引退(인퇴)"]}],"reading":"절의렴퇴","meaning":"절개와 의리, 청렴과 사양","story":"절개(節)와 의리(義), 청렴(廉)과 사양(退)은 군자의 네 가지 덕목입니다.","storyDetail":"절의염퇴(節義廉退)는 선비가 갖추어야 할 핵심 품성입니다.","keywords":["절의","청렴","사양"]},
  {"id":96,"text":"顚沛匪虧","chars":[{"char":"顚","eum":"전","hoon":"넘어질 전","strokes":19,"radical":"頁","origin":"형성","derived":["顚倒(전도)","顚覆(전복)"]},{"char":"沛","eum":"패","hoon":"넘칠 패","strokes":7,"radical":"水","origin":"형성","derived":["沛然(패연)","顚沛(전패)"]},{"char":"匪","eum":"비","hoon":"아닐 비","strokes":10,"radical":"匚","origin":"형성","derived":["匪賊(비적)"]},{"char":"虧","eum":"휴","hoon":"이지러질 휴","strokes":17,"radical":"虍","origin":"형성","derived":["虧損(휴손)"]}],"reading":"전패비휴","meaning":"넘어지는 때에도 어기지 않는다","story":"넘어지고(顚) 자빠지는(沛) 때에도 절의염퇴를 이지러뜨리지(虧) 않습니다(匪).","storyDetail":"《논어》의 '전패에도 반드시 이에 있다(顚沛必於是)'와 호응합니다.","keywords":["절개","환난","논어"]},
  {"id":97,"text":"性靜情逸","chars":[{"char":"性","eum":"성","hoon":"성품 성","strokes":8,"radical":"心","origin":"형성","derived":["性格(성격)","本性(본성)"]},{"char":"靜","eum":"정","hoon":"고요할 정","strokes":16,"radical":"靑","origin":"형성","derived":["靜寂(정적)","靜止(정지)"]},{"char":"情","eum":"정","hoon":"뜻 정","strokes":11,"radical":"心","origin":"형성","derived":["感情(감정)","情緖(정서)"]},{"char":"逸","eum":"일","hoon":"편안할 일","strokes":11,"radical":"辵","origin":"형성","derived":["安逸(안일)","逸話(일화)"]}],"reading":"성정정일","meaning":"성품이 고요하면 마음이 편안하고","story":"성품(性)이 고요하면(靜) 마음(情)이 편안합니다(逸).","storyDetail":"마음을 고요히 하면 감정이 안정되어 여유가 생긴다는 수양론입니다.","keywords":["성정","고요","수양"]},
  {"id":98,"text":"心動神疲","chars":[{"char":"心","eum":"심","hoon":"마음 심","strokes":4,"radical":"心","origin":"상형","derived":["心理(심리)","中心(중심)"]},{"char":"動","eum":"동","hoon":"움직일 동","strokes":11,"radical":"力","origin":"형성","derived":["運動(운동)","動物(동물)"]},{"char":"神","eum":"신","hoon":"귀신 신","strokes":10,"radical":"示","origin":"형성","derived":["精神(정신)","神靈(신령)"]},{"char":"疲","eum":"피","hoon":"피곤할 피","strokes":10,"radical":"疒","origin":"형성","derived":["疲勞(피로)","疲困(피곤)"]}],"reading":"심동신피","meaning":"마음이 흔들리면 정신이 피로하다","story":"마음(心)이 흔들리면(動) 정신(神)이 피곤해집니다(疲).","storyDetail":"성정정일과 대구로, 마음의 동요가 정신을 피로하게 만든다는 경계입니다.","keywords":["마음","동요","경계"]},
  {"id":99,"text":"守眞志滿","chars":[{"char":"守","eum":"수","hoon":"지킬 수","strokes":6,"radical":"宀","origin":"형성","derived":["守護(수호)","保守(보수)"]},{"char":"眞","eum":"진","hoon":"참 진","strokes":10,"radical":"目","origin":"형성","derived":["眞實(진실)","眞理(진리)"]},{"char":"志","eum":"지","hoon":"뜻 지","strokes":7,"radical":"心","origin":"형성","derived":["意志(의지)","志向(지향)"]},{"char":"滿","eum":"만","hoon":"찰 만","strokes":14,"radical":"水","origin":"형성","derived":["滿足(만족)","充滿(충만)"]}],"reading":"수진지만","meaning":"참됨을 지키면 뜻이 충만하고","story":"참됨(眞)을 지키면(守) 뜻(志)이 충만해집니다(滿).","storyDetail":"진실된 마음을 유지하면 내면이 풍요로워진다는 도가적 수양론입니다.","keywords":["진실","충만","수양"]},
  {"id":100,"text":"逐物意移","chars":[{"char":"逐","eum":"축","hoon":"쫓을 축","strokes":10,"radical":"辵","origin":"형성","derived":["追逐(추축)","驅逐(구축)"]},{"char":"物","eum":"물","hoon":"만물 물","strokes":8,"radical":"牛","origin":"형성","derived":["物質(물질)","動物(동물)"]},{"char":"意","eum":"의","hoon":"뜻 의","strokes":13,"radical":"心","origin":"형성","derived":["意味(의미)","意志(의지)"]},{"char":"移","eum":"이","hoon":"옮길 이","strokes":11,"radical":"禾","origin":"형성","derived":["移動(이동)","移住(이주)"]}],"reading":"축물의이","meaning":"만물을 쫓으면 뜻이 흔들린다","story":"만물(物)을 쫓으면(逐) 뜻(意)이 흔들립니다(移).","storyDetail":"수진지만과 대구로, 외물에 마음을 빼앗기면 본래의 뜻이 변한다는 경계입니다.","keywords":["외물","경계","뜻"]}
]
